setup.py
Cetacean.egg-info/PKG-INFO
Cetacean.egg-info/SOURCES.txt
Cetacean.egg-info/dependency_links.txt
Cetacean.egg-info/pbr.json
Cetacean.egg-info/top_level.txt
cetacean/__init__.py
cetacean/embedded_resource.py
cetacean/embedded_resource_collection.py
cetacean/resource.py
spec/__init__.py
spec/acceptance_spec.py